ValorPossivel/ValorPossivel.py
ValorPossivel/__init__.py
ValorPossivel-0.1.dist-info/METADATA
ValorPossivel-0.1.dist-info/WHEEL
ValorPossivel-0.1.dist-info/top_level.txt
ValorPossivel-0.1.dist-info/RECORD
