Metadata-Version: 2.1
Name: ValorPossivel
Version: 0.1
Summary: Um teste para API.
Home-page: https://github.com/lrzcalmon/Repo_Git_Api
Author: LRZCalmon / Curso FIAP
Author-email: ricardocalmon@gmail.com
Classifier: Programming Language :: Python :: 3
Classifier: License :: OSI Approved :: MIT License
Classifier: Operating System :: OS Independent
Requires-Python: >=3.6
